economics/__init__.py
economics/formulas.py
econometricMethodsESAN-0.0.0.1.dist-info/METADATA
econometricMethodsESAN-0.0.0.1.dist-info/WHEEL
econometricMethodsESAN-0.0.0.1.dist-info/top_level.txt
econometricMethodsESAN-0.0.0.1.dist-info/RECORD
